kubectl_mcp_tool/__init__ copy.py
kubectl_mcp_tool/__init__.py
kubectl_mcp_tool/__main__.py
kubectl_mcp_tool/claude_json_fix.py
kubectl_mcp_tool/claude_json_fix_v3.py
kubectl_mcp_tool/claude_message_framing.py
kubectl_mcp_tool/cli.py
kubectl_mcp_tool/cursor_wrapper.py
kubectl_mcp_tool/diagnostics.py
kubectl_mcp_tool/enhanced_json_fix.py
kubectl_mcp_tool/fastmcp_patch.py
kubectl_mcp_tool/fastmcp_wrapper.py
kubectl_mcp_tool/mcp_kubectl_tool.py
kubectl_mcp_tool/mcp_server.py
kubectl_mcp_tool/minimal_wrapper.py
kubectl_mcp_tool/natural_language.py
kubectl_mcp_tool/simple_ping.py
kubectl_mcp_tool/simple_server.py
kubectl_mcp_tool/taskgroup_fix.py
kubectl_mcp_tool/cli/__init__.py
kubectl_mcp_tool/cli/__main__.py
kubectl_mcp_tool/cli/cli.py
kubectl_mcp_tool/core/__init__.py
kubectl_mcp_tool/core/kubernetes_ops.py
kubectl_mcp_tool/core/mcp_server.py
kubectl_mcp_tool-1.2.0.dist-info/licenses/LICENSE
kubectl_mcp_tool-1.2.0.dist-info/METADATA
kubectl_mcp_tool-1.2.0.dist-info/WHEEL
kubectl_mcp_tool-1.2.0.dist-info/entry_points.txt
kubectl_mcp_tool-1.2.0.dist-info/top_level.txt
kubectl_mcp_tool-1.2.0.dist-info/RECORD
