Metadata-Version: 2.4
Name: kubectl-mcp-tool
Version: 1.2.0
Summary: A Model Context Protocol (MCP) server for Kubernetes
Home-page: https://github.com/rohitg00/kubectl-mcp-server
Author: Rohit Ghumare
Author-email: ghumare64@gmail.com
Classifier: Programming Language :: Python :: 3
Classifier: Programming Language :: Python :: 3.9
Classifier: Programming Language :: Python :: 3.10
Classifier: License :: OSI Approved :: MIT License
Classifier: Operating System :: OS Independent
Requires-Python: >=3.9
License-File: LICENSE
Requires-Dist: mcp>=1.5.0
Requires-Dist: pydantic>=2.0.0
Requires-Dist: fastapi>=0.100.0
Requires-Dist: uvicorn>=0.22.0
Requires-Dist: kubernetes>=28.1.0
Requires-Dist: PyYAML>=6.0.1
Requires-Dist: requests>=2.31.0
Requires-Dist: urllib3>=2.1.0
Requires-Dist: websocket-client>=1.7.0
Requires-Dist: jsonschema>=4.20.0
Requires-Dist: cryptography>=42.0.2
Requires-Dist: rich>=13.0.0
Requires-Dist: aiohttp>=3.8.0
Requires-Dist: aiohttp-sse>=2.1.0
Dynamic: author
Dynamic: author-email
Dynamic: classifier
Dynamic: description
Dynamic: description-content-type
Dynamic: home-page
Dynamic: license-file
Dynamic: requires-dist
Dynamic: requires-python
Dynamic: summary
